{    "casePartID": 1,    "connectTimeout": 6000,    "create_time": "2024-03-14 17:39:16",    "creator": 1,    "creatorName": "admin",    "desc": "校验草签列表第一个合同 预成交业绩生成",    "http": "HTTP",    "id": 9,    "level": "P1",    "projectID": 1,    "responseTimeout": 6000,    "status": "NORMAL",    "steps": [        {            "afterFunc": "resp =  response.json()\nrows = resp.get(\"data\").get(\"rows\")\nif rows:\n    conId = rows[0].get(\"conId\")\n    ",            "asserts": [                {                    "assertOpt": "==",                    "desc": "断言code",                    "expect": "0",                    "extraOpt": "jsonpath",                    "extraValue": "$.code",                    "extraValueType": "integer",                    "id": 1710409479939                }            ],            "beforeFunc": "today = date()",            "beforeParams": [                {                    "id": 1710409175360,                    "key": "username",                    "target": "5",                    "value": "625005"                }            ],            "beforeStructure": [                {                    "city": "beijing",                    "key": "_cookie",                    "name": "cookie",                    "target": "6",                    "username": "{{username}}"                }            ],            "body": {                "beginCrtDttm": "{{today}}",                "contractStatus": 1,                "currPage": 1,                "currentPageIndex": 1,                "currentPageSize": 10,                "currentpageindex": 1,                "currentpagesize": 10,                "pageIndex": 1,                "pageNum": 1,                "pageSize": 10,                "pageindex": 1,                "pagesize": 10            },            "desc": "查询合同 查询第一个",            "headers": [                {                    "desc": "登陆人cookie",                    "id": 1710409428657,                    "key": "Cookie",                    "value": "sid={{_cookie}} "                }            ],            "host": "886590a2",            "method": "POST",            "name": "查询合同",            "step": 0,            "url": "/sign/sign/signthecontract/contractinquiry"        },        {            "asserts": [                {                    "assertOpt": "==",                    "desc": "断言code",                    "expect": "0",                    "extraOpt": "jsonpath",                    "extraValue": "$.code",                    "extraValueType": "integer",                    "id": 1710409963145                },                {                    "assertOpt": "<",                    "desc": "断言业绩表",                    "expect": "0",                    "extraOpt": "jsonpath",                    "extraValue": "$.data.prorateDetailList.length()",                    "extraValueType": "integer",                    "id": 1710409963960                }            ],            "body": null,            "desc": "预分单业绩check生成",            "headers": [                {                    "id": 1710409937611,                    "key": "Cookie",                    "value": "sid={{_cookie}} "                }            ],            "host": "886590a2",            "method": "GET",            "name": "预成交业绩check",            "params": [                {                    "id": 1710410335445,                    "key": "contractId",                    "value": "{{conId}}"                }            ],            "step": 1,            "url": "/perf/perfProrateEstimate/prorateDetailEstimate"        },        {            "asserts": [                {                    "assertOpt": "==",                    "desc": "断言code",                    "expect": "0",                    "extraOpt": "jsonpath",                    "extraValue": "$.code",                    "extraValueType": "integer",                    "id": 1710410554195                },                {                    "assertOpt": "<",                    "desc": "断言长度",                    "expect": "0",                    "extraOpt": "jsonpath",                    "extraValue": "$.data.length()",                    "extraValueType": "integer",                    "id": 1710410555304                }            ],            "desc": "预成交业绩日志check",            "headers": [                {                    "id": 1710410539198,                    "key": "Cookie",                    "value": "sid= {{_cookie}} "                }            ],            "host": "886590a2",            "method": "GET",            "name": "预成交业绩日志check",            "params": [                {                    "id": 1710410486216,                    "key": "contractId",                    "value": "{{conId}}"                }            ],            "step": 2,            "url": "/perf/perfProrateEstimate/getPerfProrateEstimateTrace"        }    ],    "taskID": null,    "title": "预成交业绩check",    "uid": "bb1b114e",    "update_time": "2024-06-12 18:05:22",    "updater": 1,    "updaterName": "admin"}